{
  "nodes": [
    { "data": { "id": "html_base", "label": "HTML 基础结构" } },
    { "data": { "id": "h_element", "label": "使用h元素表示标题" } },
    { "data": { "id": "p_element", "label": "用 <p> 段落组织文本" } },
    { "data": { "id": "list_element", "label": "创建列表" } },
    { "data": { "id": "img_element", "label": "插入图片" } },
    { "data": { "id": "label_element", "label": "创建复选框" } },
    { "data": { "id": "table_element", "label": "构建基本表格" } },
    { "data": { "id": "js", "label": "js" } },
    { "data": { "id": "css_intro", "label": "了解什么是 CSS" } },
    { "data": { "id": "css_inline", "label": "使用 style 设置行内样式" } },
    { "data": { "id": "css_selector", "label": "通过选择器应用样式" } },
    { "data": { "id": "css_color", "label": "设置颜色与背景" } },
    { "data": { "id": "css_box", "label": "掌握盒模型" } },
    { "data": { "id": "css_layout", "label": "使用 Flex 进行布局" } }
  ],
  "edges": [
    { "data": { "source": "html_base", "target": "h_element" } },
    { "data": { "source": "h_element", "target": "p_element" } },
    { "data": { "source": "p_element", "target": "list_element" } },
    { "data": { "source": "list_element", "target": "img_element" } },
    { "data": { "source": "img_element", "target": "label_element" } },
    { "data": { "source": "label_element", "target": "table_element" } },
    { "data": { "source": "table_element", "target": "js" } },

    { "data": { "source": "html_base", "target": "css_intro" } },
    { "data": { "source": "css_intro", "target": "css_inline" } },
    { "data": { "source": "css_inline", "target": "css_selector" } },
    { "data": { "source": "css_selector", "target": "css_color" } },
    { "data": { "source": "css_color", "target": "css_box" } },
    { "data": { "source": "css_box", "target": "css_layout" } }
  ]
}
